lmselfie/__init__.py
lmselfie-0.0.2.dist-info/DESCRIPTION.rst
lmselfie-0.0.2.dist-info/METADATA
lmselfie-0.0.2.dist-info/RECORD
lmselfie-0.0.2.dist-info/WHEEL
lmselfie-0.0.2.dist-info/entry_points.txt
lmselfie-0.0.2.dist-info/metadata.json
lmselfie-0.0.2.dist-info/top_level.txt
