Metadata-Version: 2.0
Name: lmselfie
Version: 0.0.2
Summary: Software para cabina de selfie
Home-page: https://bitbucket.org/TuTa1612/lmselfie
Author: Lucas Saavedra
Author-email: saavedralucasemanuel@gmail.com
License: UNKNOWN
Platform: UNKNOWN
